hreports/__init__.py
hreports/cli.py
hreports/config.py
hreports/hreports.py
hreports/template_filters.py
hreports/templates/invoice_de.tpl
hreports-0.2.1.dist-info/DESCRIPTION.rst
hreports-0.2.1.dist-info/METADATA
hreports-0.2.1.dist-info/RECORD
hreports-0.2.1.dist-info/WHEEL
hreports-0.2.1.dist-info/entry_points.txt
hreports-0.2.1.dist-info/metadata.json
hreports-0.2.1.dist-info/top_level.txt
