Metadata-Version: 2.0
Name: hreports
Version: 0.2.1
Summary: A simple wrapper to create and manage reports based on hledger queries.
Home-page: https://github.com/msmart/hreports
Author: Michael Martinides
Author-email: msmart@posteo.de
License: MIT license
Keywords: hreports
Platform: UNKNOWN
Classifier: Development Status :: 2 - Pre-Alpha
Classifier: Intended Audience :: Developers
Classifier: License :: OSI Approved :: MIT License
Classifier: Natural Language :: English
Classifier: Programming Language :: Python :: 2
Classifier: Programming Language :: Python :: 2.7
Classifier: Programming Language :: Python :: 3
Classifier: Programming Language :: Python :: 3.4
Classifier: Programming Language :: Python :: 3.5
Requires-Dist: Click (>=6.0)
Requires-Dist: PyYAML (>=3.12)
Requires-Dist: Jinja2 (>=2.10)
